.gitignore
LICENSE
README.md
pyproject.toml
requirements.txt
setup.cfg
setup.py
__pycache__/model_calls.cpython-312.pyc
__pycache__/pytra.cpython-312.pyc
__pycache__/pytra_tui.cpython-312.pyc
figures/demo.gif
src/pydift/__init__.py
src/pydift/model_calls.py
src/pydift/pydift.py
src/pydift/pydift_tui.py
src/pydift.egg-info/PKG-INFO
src/pydift.egg-info/SOURCES.txt
src/pydift.egg-info/dependency_links.txt
src/pydift.egg-info/entry_points.txt
src/pydift.egg-info/requires.txt
src/pydift.egg-info/top_level.txt
src/pydift/data/model_conf.yaml
src/pydift/data/pydift_conf.yaml