Metadata-Version: 2.1
Name: pydift
Version: 0.1.1
Summary: A simple version-tracking tool for research code development.
Home-page: https://github.com/alonj/pydift
Author-email: Alon Jacoby <alonj4@gmail.com>
License: MIT
Project-URL: Homepage, https://github.com/alonj/pydift
Classifier: Programming Language :: Python :: 3
Classifier: License :: OSI Approved :: MIT License
Classifier: Operating System :: OS Independent
Requires-Python: >=3.6
